image_attendant/__init__.py
image_attendant/compression.py
image_attendant/image_io.py
image_attendant/mpl.py
image_attendant/rebin.py
image_attendant/utility.py
image_attendant-2020.7.29.dist-info/LICENSE
image_attendant-2020.7.29.dist-info/METADATA
image_attendant-2020.7.29.dist-info/WHEEL
image_attendant-2020.7.29.dist-info/top_level.txt
image_attendant-2020.7.29.dist-info/RECORD
