Metadata-Version: 2.1
Name: image-attendant
Version: 2020.7.29
Summary: Helpful image processing functions
Home-page: https://github.com/who8mylunch/image_attendant
Author: Pierre V. Villeneuve
Author-email: pierre.villeneuve@gmail.com
License: MIT
Platform: UNKNOWN
Classifier: Development Status :: 3 - Alpha
Classifier: Intended Audience :: Developers
Classifier: Programming Language :: Python :: 3
Requires-Dist: numpy
Requires-Dist: requests
Requires-Dist: Pillow
